dwcl/DashWindowCloseListener.py
dwcl/__init__.py
dwcl/_imports_.py
dwcl/dwcl.min.js
dwcl/dwcl.min.js.map
dwcl/metadata.json
dwcl/package-info.json
dwcl-1.0.3.dist-info/LICENSE
dwcl-1.0.3.dist-info/METADATA
dwcl-1.0.3.dist-info/WHEEL
dwcl-1.0.3.dist-info/top_level.txt
dwcl-1.0.3.dist-info/RECORD
