Metadata-Version: 2.1
Name: dwcl
Version: 1.0.3
Summary: A Dash Component that catches a the window close event and updates it's status. This can be used to stop the Dash server when the user closes his window, which is useful when using Dash apps as part of a multi step a workflow.
Home-page: https://github.com/raymon-ai/dwcl
Author: Karel Vanhoorebeeck <karel@raymon.ai>
License: MIT
Platform: UNKNOWN
Classifier: Framework :: Dash
